trebuchet/__init__.py
trebuchet/__main__.py
trebuchet/parse.py
aoc_trebuchet-1.1.0.dist-info/LICENSE
aoc_trebuchet-1.1.0.dist-info/METADATA
aoc_trebuchet-1.1.0.dist-info/WHEEL
aoc_trebuchet-1.1.0.dist-info/entry_points.txt
aoc_trebuchet-1.1.0.dist-info/RECORD
