Metadata-Version: 2.1
Name: aoc-trebuchet
Version: 1.1.0
Summary: Python implementation of Advent of Code 2023 Day 1
License: MIT
Author: TonyGrif
Author-email: TonyGriffin2000@gmail.com
Maintainer: TonyGrif
Maintainer-email: TonyGriffin2000@gmail.com
Requires-Python: >=3.8,<4.0
Classifier: License :: OSI Approved :: MIT License
Classifier: Programming Language :: Python :: 3
Classifier: Programming Language :: Python :: 3.8
Classifier: Programming Language :: Python :: 3.9
Classifier: Programming Language :: Python :: 3.10
Classifier: Programming Language :: Python :: 3.11
Classifier: Programming Language :: Python :: 3.12
Classifier: Programming Language :: Python :: 3.13
Requires-Dist: click (>=8.1.7,<9.0.0)
